aihorde/__init__.py
aihorde/client.py
aihorde/models.py
aihorde-0.3.dist-info/LICENSE
aihorde-0.3.dist-info/METADATA
aihorde-0.3.dist-info/WHEEL
aihorde-0.3.dist-info/top_level.txt
aihorde-0.3.dist-info/RECORD
