Metadata-Version: 2.1
Name: aihorde
Version: 0.3
Summary: Python client for AI Horde API
Author-email: "LapisMYT (Nikita Ugnich)" <nikitagavrilin005@gmail.com>
Project-URL: Homepage, https://github.com/lapismyt/pyAIHorde
Classifier: Development Status :: 4 - Beta
Classifier: Framework :: aiohttp
Classifier: Intended Audience :: Developers
Classifier: Programming Language :: Python :: 3.11
Classifier: Programming Language :: Python :: 3.12
Classifier: License :: OSI Approved :: GNU General Public License v3 (GPLv3)
Classifier: Topic :: Scientific/Engineering :: Artificial Intelligence
Classifier: Topic :: Scientific/Engineering :: Image Processing
Classifier: Topic :: Scientific/Engineering :: Visualization
Classifier: Topic :: Software Development :: Libraries
Classifier: Topic :: Software Development :: Libraries :: Python Modules
Classifier: Topic :: Text Processing
Classifier: Typing :: Typed
License-File: LICENSE
Requires-Dist: aiohttp
Requires-Dist: msgspec
